simple_launch.py
simple_launch-0.1.1.dist-info/LICENSE.txt
simple_launch-0.1.1.dist-info/METADATA
simple_launch-0.1.1.dist-info/WHEEL
simple_launch-0.1.1.dist-info/entry_points.txt
simple_launch-0.1.1.dist-info/top_level.txt
simple_launch-0.1.1.dist-info/RECORD
