Metadata-Version: 2.1
Name: simple-launch
Version: 0.1.1
Summary: A simple launcher for Robotics applications
Author-email: John Wason <wason@wasontech.com>
License: Apache-2.0
Requires-Python: >=3.8
License-File: LICENSE.txt
Requires-Dist: pyyaml
Requires-Dist: appdirs
Requires-Dist: simple-launch-process
Provides-Extra: test
Requires-Dist: pytest ; extra == 'test'
Requires-Dist: pywin32 ; (platform_system == "Windows") and extra == 'test'
